catch_them_all/__init__.py
catch_them_all/console.py
catch_them_all/core.py
catch_them_all/error_report.py
catch_them_all/excepthook.py
catch_them_all/formatter.py
catch_them_all/registry.py
catch_them_all/themes.py
catch_them_all/utils.py
catch_them_all-1.0.1.dist-info/METADATA
catch_them_all-1.0.1.dist-info/WHEEL
catch_them_all-1.0.1.dist-info/licenses/LICENSE.txt
catch_them_all-1.0.1.dist-info/RECORD
