Metadata-Version: 2.1
Name: catch-them-all
Version: 1.0.1
Summary: Not just a traceback formatter — but a universal exception handler. A single @decorator that transforms every exception into a structured, multi-format report
Project-URL: Homepage, https://github.com/AnasseGX/catch-them-all
Project-URL: Repository, https://github.com/AnasseGX/catch-them-all
Project-URL: Issues, https://github.com/AnasseGX/catch-them-all/issues
Author-email: Anasse Gassab <anasse.gsb@gmail.com>
License: MIT License
License-File: LICENSE.txt
Keywords: colors,customize,debug,debugging,decorator,decorators,excepthook,exception,exception-handling,exceptions,logging,pokemon,pretty,pretty-print,pretty-traceback,rich,structured-report,traceback
Classifier: Development Status :: 5 - Production/Stable
Classifier: Intended Audience :: Developers
Classifier: License :: OSI Approved :: MIT License
Classifier: Operating System :: OS Independent
Classifier: Programming Language :: Python :: 3
Classifier: Programming Language :: Python :: 3.8
Classifier: Programming Language :: Python :: 3.9
Classifier: Programming Language :: Python :: 3.10
Classifier: Programming Language :: Python :: 3.11
Classifier: Programming Language :: Python :: 3.12
Classifier: Topic :: Software Development :: Debuggers
Classifier: Topic :: Software Development :: Libraries :: Python Modules
Requires-Python: >=3.8
Requires-Dist: rich>=13.0
Provides-Extra: dev
Requires-Dist: black; extra == 'dev'
Requires-Dist: mypy; extra == 'dev'
Requires-Dist: ruff; extra == 'dev'
Provides-Extra: test
Requires-Dist: numpy==2.3.5; extra == 'test'
Requires-Dist: pixel-pretender==1.0.1; extra == 'test'
Requires-Dist: playwright==1.56.0; extra == 'test'
Requires-Dist: pyautogui==0.9.54; extra == 'test'
Requires-Dist: requests==2.32.5; extra == 'test'
Requires-Dist: rich==14.2.0; extra == 'test'
Requires-Dist: sqlalchemy==2.0.45; extra == 'test'
